image_processing_rbiegelmeyer/__init__.py
image_processing_rbiegelmeyer/processing/__init__.py
image_processing_rbiegelmeyer/processing/combination.py
image_processing_rbiegelmeyer/processing/transformation.py
image_processing_rbiegelmeyer/utils/__init__.py
image_processing_rbiegelmeyer/utils/io.py
image_processing_rbiegelmeyer/utils/plot.py
image_processing_rbiegelmeyer-0.0.2.dist-info/METADATA
image_processing_rbiegelmeyer-0.0.2.dist-info/WHEEL
image_processing_rbiegelmeyer-0.0.2.dist-info/top_level.txt
image_processing_rbiegelmeyer-0.0.2.dist-info/RECORD
